conflutools/__init__.py
conflutools/cli.py
conflutools/connection.py
conflutools/export.py
conflutools-0.2.0.dist-info/METADATA
conflutools-0.2.0.dist-info/WHEEL
conflutools-0.2.0.dist-info/entry_points.txt
conflutools-0.2.0.dist-info/RECORD
